CHANGES.md
LICENSE
MANIFEST.in
README.md
setup.cfg
setup.py
botool/__init__.py
botool/common.py
botool.egg-info/PKG-INFO
botool.egg-info/SOURCES.txt
botool.egg-info/dependency_links.txt
botool.egg-info/entry_points.txt
botool.egg-info/not-zip-safe
botool.egg-info/requires.txt
botool.egg-info/top_level.txt
botool/scripts/create_users.py