Metadata-Version: 1.1
Name: botool
Version: 0.1.1
Summary: A botocore helper lib
Home-page: https://github.com/reedobrien/botool
Author: Reed O'Brien
Author-email: reed.foss@reedobrien.com
License: BSD-derived. See LICENSE file
Keywords: AWS botocore
Platform: UNKNOWN
Classifier: Intended Audience :: Developers
Classifier: Programming Language :: Python
